kma/__init__.py
kma/current.py
kma/exceptions.py
kma/forecast.py
kma/ipinfo.py
kma/kma.py
kma/xy_converter.py
kma-0.3.0.dist-info/DESCRIPTION.rst
kma-0.3.0.dist-info/METADATA
kma-0.3.0.dist-info/RECORD
kma-0.3.0.dist-info/WHEEL
kma-0.3.0.dist-info/metadata.json
kma-0.3.0.dist-info/top_level.txt
