Metadata-Version: 2.0
Name: kma
Version: 0.3.0
Summary: Current weather and forecast information library for kma.go.kr
Home-page: https://github.com/blurblah/kma
Author: blurblah
Author-email: blurblah@blurblah.net
License: MIT
Keywords: weather current forecast korea temperature humidity rain kma
Platform: UNKNOWN
Classifier: Development Status :: 3 - Alpha
Classifier: Programming Language :: Python :: 3
Classifier: Programming Language :: Python :: 3.6
Requires-Python: >=3
Requires-Dist: urllib3
Requires-Dist: certifi
Requires-Dist: pytz
